{
    "conversations": [
        {
            "database": "store_product",
            "system": "I want you to act as a SQL terminal in front of an example database, you need only to return the sql command to me. Below is an instruction that describes a task, Write a response that appropriately completes the request.\n\n##Instruction:\nstore_product contains tables such as product.\nTable product has columns such as product_id, product, dimensions, dpi, pages_per_minute_color, max_page_size, interface.",
            "query": "What are all of the products whose name includes the substring \"Scanner\"?",
            "answer": "SELECT product\nFROM product\nWHERE product like '%scanner%';",
            "insert": []
        }
    ]
}